sismoscl/.dockerignore
sismoscl/.editorconfig
sismoscl/.github/.stale.yml
sismoscl/.github/ISSUE_TEMPLATE/bug_report.md
sismoscl/.github/ISSUE_TEMPLATE/config.yml
sismoscl/.github/ISSUE_TEMPLATE/feature_request.md
sismoscl/.github/ISSUE_TEMPLATE/question.md
sismoscl/.github/PULL_REQUEST_TEMPLATE.md
sismoscl/.github/dependabot.yml
sismoscl/.github/release-drafter.yml
sismoscl/.github/workflows/build.yml
sismoscl/.github/workflows/greetings.yml
sismoscl/.github/workflows/release-drafter.yml
sismoscl/.gitignore
sismoscl/.pre-commit-config.yaml
sismoscl/__init__.py
sismoscl/__main__.py
sismoscl/sismos.py
sismoscl-0.1.1.dist-info/entry_points.txt
sismoscl-0.1.1.dist-info/LICENSE
sismoscl-0.1.1.dist-info/WHEEL
sismoscl-0.1.1.dist-info/METADATA
sismoscl-0.1.1.dist-info/RECORD
